task3/counter.sv
module counter #(
    parameter WIDTH = 8
)(
    // interface signals
    input logic clk,
    input logic rst,
    input logic en,
    input logic storedVal,
    input logic lastEn,
    output logic [WIDTH-1:0] count
);

always_ff @ (posedge clk)
    if (rst) count <= {WIDTH{1'b0}};
    else    if (en)   count <= storedVal; 
            else count <= count + {{WIDTH-1{1'b0}}, 1'b1};
            // count <= count + {{WIDTH-1{1'b0}}, en}; // this code is for the second part of task 3
    ;
    
endmodule

task3/counter.vcd
$version Generated by VerilatedVcd $end
$date Wed Oct 26 12:44:11 2022 $end
$timescale 1ps $end

 $scope module TOP $end
  $var wire  1 # clk $end
  $var wire  8 ( count [7:0] $end
  $var wire  1 % en $end
  $var wire  1 ' lastEn $end
  $var wire  1 $ rst $end
  $var wire  1 & storedVal $end
  $scope module counter $end
   $var wire 32 ) WIDTH [31:0] $end
   $var wire  1 # clk $end
   $var wire  8 ( count [7:0] $end
   $var wire  1 % en $end
   $var wire  1 ' lastEn $end
   $var wire  1 $ rst $end
   $var wire  1 & storedVal $end
  $upscope $end
 $upscope $end
$enddefinitions $end


#0
1#
0$
0%
0&
0'
b00000000 (
b00000000000000000000000000001000 )
#1
0#
#2
1#
3&
b00000001 (
#3
0#
#4
1#
b00000010 (
#5
0#
#6
1#
b00000011 (
#7
0#
#8
1#
b00000100 (
#9
0#
#10
1#
b00000101 (
#11
0#
#12
1#
b00000110 (
#13
0#
#14
1#
1%
b00000111 (
#15
0#
#16
1#
0%
b00110011 (
#17
0#
#18
1#
b00110100 (
#19
0#
#20
1#
b00110101 (
#21
0#
#22
1#
b00110110 (
#23
0#
#24
1#
b00110111 (
#25
0#
#26
1#
b00111000 (
#27
0#
#28
1#
b00111001 (
#29
0#
#30
1#
1&
b00111010 (
#31
0#
#32
1#
?&
b00111011 (
#33
0#
#34
1#
=&
b00111100 (
#35
0#
#36
1#
b00111101 (
#37
0#
#38
1#
;&
b00111110 (
#39
0#
#40
1#
9&
b00111111 (
#41
0#
#42
1#
8&
b01000000 (
#43
0#
#44
1#
b01000001 (
#45
0#
#46
1#
b01000010 (
#47
0#
#48
1#
1%
b01000011 (
#49
0#
#50
1#
0%
b00101000 (
#51
0#
#52
1#
b00101001 (
#53
0#
#54
1#
b00101010 (
#55
0#
#56
1#
b00101011 (
#57
0#
#58
1#
;&
b00101100 (
#59
0#
#60
1#
0&
b00101101 (
#61
0#
#62
1#
1&
b00101110 (
#63
0#
#64
1#
3&
b00101111 (
#65
0#
#66
1#
5&
b00110000 (
#67
0#
#68
1#
:&
b00110001 (
#69
0#
#70
1#
;&
b00110010 (
#71
0#
#72
1#
b00110011 (
#73
0#
#74
1#
<&
b00110100 (
#75
0#
#76
1#
>&
b00110101 (
#77
0#
#78
1#
b00110110 (
#79
0#
#80
1#
b00110111 (
#81
0#
#82
1#
b00111000 (
#83
0#
#84
1#
b00111001 (
#85
0#
#86
1#
1%
b00111010 (
#87
0#
#88
1#
0%
b00111110 (
#89
0#
#90
1#
b00111111 (
#91
0#
#92
1#
b01000000 (
#93
0#
#94
1#
b01000001 (
#95
0#
#96
1#
b01000010 (
#97
0#
#98
1#
b01000011 (
#99
0#
#100
1#
b01000100 (
#101
0#
#102
1#
b01000101 (
#103
0#
#104
1#
b01000110 (
#105
0#
#106
1#
b01000111 (
#107
0#
#108
1#
b01001000 (
#109
0#
#110
1#
b01001001 (
#111
0#
#112
1#
b01001010 (
#113
0#
#114
1#
b01001011 (
#115
0#
#116
1#
b01001100 (
#117
0#
#118
1#
b01001101 (
#119
0#
#120
1#
b01001110 (
#121
0#
#122
1#
b01001111 (
#123
0#
#124
1#
b01010000 (
#125
0#
#126
1#
b01010001 (
#127
0#
#128
1#
b01010010 (
#129
0#
#130
1#
b01010011 (
#131
0#
#132
1#
b01010100 (
#133
0#
#134
1#
b01010101 (
#135
0#
#136
1#
b01010110 (
#137
0#
#138
1#
b01010111 (
#139
0#
#140
1#
b01011000 (
#141
0#
#142
1#
b01011001 (
#143
0#
#144
1#
b01011010 (
#145
0#
#146
1#
b01011011 (
#147
0#
#148
1#
b01011100 (
#149
0#
#150
1#
b01011101 (
#151
0#
#152
1#
b01011110 (
#153
0#
#154
1#
b01011111 (
#155
0#
#156
1#
b01100000 (
#157
0#
#158
1#
b01100001 (
#159
0#
#160
1#
b01100010 (
#161
0#
#162
1#
b01100011 (
#163
0#
#164
1#
b01100100 (
#165
0#
#166
1#
b01100101 (
#167
0#
#168
1#
b01100110 (
#169
0#
#170
1#
b01100111 (
#171
0#
#172
1#
b01101000 (
#173
0#
#174
1#
b01101001 (
#175
0#
#176
1#
b01101010 (
#177
0#
#178
1#
b01101011 (
#179
0#
#180
1#
b01101100 (
#181
0#
#182
1#
b01101101 (
#183
0#
#184
1#
b01101110 (
#185
0#
#186
1#
b01101111 (
#187
0#
#188
1#
b01110000 (
#189
0#
#190
1#
b01110001 (
#191
0#
#192
1#
b01110010 (
#193
0#
#194
1#
b01110011 (
#195
0#
#196
1#
b01110100 (
#197
0#
#198
1#
b01110101 (
#199
0#
#200
1#
b01110110 (
#201
0#
#202
1#
b01110111 (
#203
0#
#204
1#
b01111000 (
#205
0#
#206
1#
b01111001 (
#207
0#
#208
1#
b01111010 (
#209
0#
#210
1#
b01111011 (
#211
0#
#212
1#
b01111100 (
#213
0#
#214
1#
b01111101 (
#215
0#
#216
1#
b01111110 (
#217
0#
#218
1#
b01111111 (
#219
0#
#220
1#
b10000000 (
#221
0#
#222
1#
b10000001 (
#223
0#
#224
1#
b10000010 (
#225
0#
#226
1#
b10000011 (
#227
0#
#228
1#
b10000100 (
#229
0#
#230
1#
b10000101 (
#231
0#
#232
1#
b10000110 (
#233
0#
#234
1#
b10000111 (
#235
0#
#236
1#
b10001000 (
#237
0#
#238
1#
b10001001 (
#239
0#
#240
1#
b10001010 (
#241
0#
#242
1#
b10001011 (
#243
0#
#244
1#
b10001100 (
#245
0#
#246
1#
b10001101 (
#247
0#
#248
1#
b10001110 (
#249
0#
#250
1#
b10001111 (
#251
0#
#252
1#
b10010000 (
#253
0#
#254
1#
b10010001 (
#255
0#
#256
1#
b10010010 (
#257
0#
#258
1#
b10010011 (
#259
0#
#260
1#
b10010100 (
#261
0#
#262
1#
b10010101 (
#263
0#
#264
1#
b10010110 (
#265
0#
#266
1#
b10010111 (
#267
0#
#268
1#
b10011000 (
#269
0#
#270
1#
b10011001 (
#271
0#
#272
1#
b10011010 (
#273
0#
#274
1#
b10011011 (
#275
0#
#276
1#
b10011100 (
#277
0#
#278
1#
b10011101 (
#279
0#
#280
1#
b10011110 (
#281
0#
#282
1#
b10011111 (
#283
0#
#284
1#
b10100000 (
#285
0#
#286
1#
b10100001 (
#287
0#
#288
1#
q&
b10100010 (
#289
0#
#290
1#
u&
b10100011 (
#291
0#
#292
1#
~&
b10100100 (
#293
0#
#294
1#
p&
b10100101 (
#295
0#
#296
1#
b10100110 (
#297
0#
#298
1#
u&
b10100111 (
#299
0#
#300
1#
v&
b10101000 (
#301
0#
#302
1#
{&
b10101001 (
#303
0#
#304
1#
b10101010 (
#305
0#
#306
1#
~&
b10101011 (
#307
0#
#308
1#
&
b10101100 (
#309
0#
#310
1#
p&
b10101101 (
#311
0#
#312
1#
s&
b10101110 (
#313
0#
#314
1#
t&
b10101111 (
#315
0#
#316
1#
b10110000 (
#317
0#
#318
1#
b10110001 (
#319
0#
#320
1#
b10110010 (
#321
0#
#322
1#
b10110011 (
#323
0#
#324
1#
b10110100 (
#325
0#
#326
1#
b10110101 (
#327
0#
#328
1#
b10110110 (
#329
0#
#330
1#
b10110111 (
#331
0#
#332
1#
b10111000 (
#333
0#
#334
1#
b10111001 (
#335
0#
#336
1#
1%
b10111010 (
#337
0#
#338
1#
0%
b01100100 (
#339
0#
#340
1#
b01100101 (
#341
0#
#342
1#
b01100110 (
#343
0#
#344
1#
b01100111 (
#345
0#
#346
1#
b01101000 (
#347
0#
#348
1#
b01101001 (
#349
0#
#350
1#
b01101010 (
#351
0#
#352
1#
b01101011 (
#353
0#
#354
1#
b01101100 (
#355
0#
#356
1#
b01101101 (
#357
0#
#358
1#
b01101110 (
#359
0#
#360
1#
b01101111 (
#361
0#
#362
1#
b01110000 (
#363
0#
#364
1#
b01110001 (
#365
0#
#366
1#
b01110010 (
#367
0#
#368
1#
b01110011 (
#369
0#
#370
1#
b01110100 (
#371
0#
#372
1#
b01110101 (
#373
0#
#374
1#
b01110110 (
#375
0#
#376
1#
b01110111 (
#377
0#
#378
1#
b01111000 (
#379
0#
#380
1#
b01111001 (
#381
0#
#382
1#
b01111010 (
#383
0#
#384
1#
b01111011 (
#385
0#
#386
1#
b01111100 (
#387
0#
#388
1#
b01111101 (
#389
0#
#390
1#
b01111110 (
#391
0#
#392
1#
b01111111 (
#393
0#
#394
1#
b10000000 (
#395
0#
#396
1#
b10000001 (
#397
0#
#398
1#
b10000010 (
#399
0#
#400
1#
b10000011 (
#401
0#
#402
1#
b10000100 (
#403
0#
#404
1#
b10000101 (
#405
0#
#406
1#
b10000110 (
#407
0#
#408
1#
b10000111 (
#409
0#
#410
1#
b10001000 (
#411
0#
#412
1#
b10001001 (
#413
0#
#414
1#
b10001010 (
#415
0#
#416
1#
b10001011 (
#417
0#
#418
1#
b10001100 (
#419
0#
#420
1#
b10001101 (
#421
0#
#422
1#
b10001110 (
#423
0#
#424
1#
b10001111 (
#425
0#
#426
1#
b10010000 (
#427
0#
#428
1#
b10010001 (
#429
0#
#430
1#
b10010010 (
#431
0#
#432
1#
b10010011 (
#433
0#
#434
1#
b10010100 (
#435
0#
#436
1#
b10010101 (
#437
0#
#438
1#
b10010110 (
#439
0#
#440
1#
b10010111 (
#441
0#
#442
1#
b10011000 (
#443
0#
#444
1#
b10011001 (
#445
0#
#446
1#
b10011010 (
#447
0#
#448
1#
b10011011 (
#449
0#
#450
1#
b10011100 (
#451
0#
#452
1#
b10011101 (
#453
0#
#454
1#
b10011110 (
#455
0#
#456
1#
b10011111 (
#457
0#
#458
1#
b10100000 (
#459
0#
#460
1#
b10100001 (
#461
0#
#462
1#
b10100010 (
#463
0#
#464
1#
b10100011 (
#465
0#
#466
1#
b10100100 (
#467
0#
#468
1#
b10100101 (
#469
0#
#470
1#
b10100110 (
#471
0#
#472
1#
b10100111 (
#473
0#
#474
1#
b10101000 (
#475
0#
#476
1#
b10101001 (
#477
0#
#478
1#
b10101010 (
#479
0#
#480
1#
b10101011 (
#481
0#
#482
1#
b10101100 (
#483
0#
#484
1#
b10101101 (
#485
0#
#486
1#
b10101110 (
#487
0#
#488
1#
b10101111 (
#489
0#
#490
1#
b10110000 (
#491
0#
#492
1#
b10110001 (
#493
0#
#494
1#
b10110010 (
#495
0#
#496
1#
b10110011 (
#497
0#
#498
1#
b10110100 (
#499
0#
#500
1#
b10110101 (
#501
0#
#502
1#
b10110110 (
#503
0#
#504
1#
b10110111 (
#505
0#
#506
1#
b10111000 (
#507
0#
#508
1#
b10111001 (
#509
0#
#510
1#
b10111010 (
#511
0#
#512
1#
b10111011 (
#513
0#
#514
1#
b10111100 (
#515
0#
#516
1#
b10111101 (
#517
0#
#518
1#
b10111110 (
#519
0#
#520
1#
b10111111 (
#521
0#
#522
1#
b11000000 (
#523
0#
#524
1#
b11000001 (
#525
0#
#526
1#
b11000010 (
#527
0#
#528
1#
b11000011 (
#529
0#
#530
1#
b11000100 (
#531
0#
#532
1#
b11000101 (
#533
0#
#534
1#
b11000110 (
#535
0#
#536
1#
b11000111 (
#537
0#
#538
1#
b11001000 (
#539
0#
#540
1#
b11001001 (
#541
0#
#542
1#
b11001010 (
#543
0#
#544
1#
b11001011 (
#545
0#
#546
1#
b11001100 (
#547
0#
#548
1#
b11001101 (
#549
0#
#550
1#
b11001110 (
#551
0#
#552
1#
b11001111 (
#553
0#
#554
1#
b11010000 (
#555
0#
#556
1#
b11010001 (
#557
0#
#558
1#
b11010010 (
#559
0#
#560
1#
b11010011 (
#561
0#
#562
1#
b11010100 (
#563
0#
#564
1#
b11010101 (
#565
0#
#566
1#
b11010110 (
#567
0#
#568
1#
b11010111 (
#569
0#
#570
1#
b11011000 (
#571
0#
#572
1#
b11011001 (
#573
0#
#574
1#
b11011010 (
#575
0#
#576
1#
b11011011 (
#577
0#
#578
1#
b11011100 (
#579
0#
#580
1#
b11011101 (
#581
0#
#582
1#
b11011110 (
#583
0#
#584
1#
b11011111 (
#585
0#
#586
1#
b11100000 (
#587
0#
#588
1#
b11100001 (
#589
0#
#590
1#
b11100010 (
#591
0#
#592
1#
b11100011 (
#593
0#
#594
1#
b11100100 (
#595
0#
#596
1#
b11100101 (
#597
0#
#598
1#
b11100110 (
